certora_cli/__init__.py
certora_cli/certoraBuild.py
certora_cli/certoraCloudIO.py
certora_cli/certoraCollectRunMetadata.py
certora_cli/certoraConfigIO.py
certora_cli/certoraDualArg.py
certora_cli/certoraRun.py
certora_cli/certoraTester.py
certora_cli/certoraUtils.py
certora_jars/Typechecker.jar
certora_jars/__init__.py
certora_cli_coinbase-2.4.1.dist-info/LICENSE
certora_cli_coinbase-2.4.1.dist-info/METADATA
certora_cli_coinbase-2.4.1.dist-info/WHEEL
certora_cli_coinbase-2.4.1.dist-info/entry_points.txt
certora_cli_coinbase-2.4.1.dist-info/top_level.txt
certora_cli_coinbase-2.4.1.dist-info/RECORD
